{"is_source_file": true, "format": "JavaScript (React JSX)", "description": "This file serves as the entry point for a React application, rendering the main App component wrapped with a ThemeProvider for theme management, and initializing the React root rendering process.", "external_files": ["react", "react-dom/client", "./App", "./theme/ThemeProvider"], "external_methods": ["createRoot"], "published": [], "classes": [], "methods": [{"name": "render", "description": "Initializes the React rendering of the application into the DOM element with id 'root', wrapping the App component with StrictMode and ThemeProvider."}], "calls": ["createRoot", "root.render"], "search-terms": ["React", "ThemeProvider", "index.jsx", "React.StrictMode", "ReactDOM", "app entry point", "initial render"], "state": 2, "file_id": 9, "knowledge_revision": 20, "git_revision": "4d171157596d66239f7d22f0f6fd9d4aac0988de", "ctags": [{"_type": "tag", "name": "container", "path": "/home/kavia/workspace/code-generation/javascript-playground-221940-221949/frontend_react_js/src/index.jsx", "pattern": "/^const container = document.getElementById(\"root\");$/", "language": "JavaScript", "kind": "constant"}, {"_type": "tag", "name": "root", "path": "/home/kavia/workspace/code-generation/javascript-playground-221940-221949/frontend_react_js/src/index.jsx", "pattern": "/^const root = createRoot(container);$/", "language": "JavaScript", "kind": "constant"}], "hash": "4dcf88862f471f56b1d250ca1c1f04e1", "format-version": 4, "code-base-name": "frontend_react_js", "filename": "frontend_react_js/src/index.jsx", "revision_history": [{"20": "4d171157596d66239f7d22f0f6fd9d4aac0988de"}]}